sphinx_expose_init_alias/__about__.py
sphinx_expose_init_alias/__init__.py
sphinx_expose_init_alias/callback.py
sphinx_expose_init_alias/documenter.py
sphinx_expose_init_alias/exception.py
sphinx_expose_init_alias-0.2.0.dist-info/METADATA
sphinx_expose_init_alias-0.2.0.dist-info/WHEEL
sphinx_expose_init_alias-0.2.0.dist-info/licenses/LICENSE
sphinx_expose_init_alias-0.2.0.dist-info/RECORD
