Metadata-Version: 2.1
Name: sphinx-expose-init-alias
Version: 0.2.0
Project-URL: Documentation, https://github.com/cmsxbc/sphinx-expose-init-alias#readme
Project-URL: Issues, https://github.com/cmsxbc/sphinx-expose-init-alias/issues
Project-URL: Source, https://github.com/cmsxbc/sphinx-expose-init-alias
Author-email: cmsxbc <i@cmsis.me>
License-File: LICENSE
Classifier: Development Status :: 4 - Beta
Classifier: Programming Language :: Python
Classifier: Programming Language :: Python :: 3.7
Classifier: Programming Language :: Python :: 3.8
Classifier: Programming Language :: Python :: 3.9
Classifier: Programming Language :: Python :: 3.10
Classifier: Programming Language :: Python :: 3.11
Classifier: Programming Language :: Python :: Implementation :: CPython
Classifier: Programming Language :: Python :: Implementation :: PyPy
Requires-Python: >=3.7
Requires-Dist: sphinx>=5.1.1
